qcsapphire/__init__.py
qcsapphire/pulser.py
qcsapphire-1.0.1.dist-info/LICENSE
qcsapphire-1.0.1.dist-info/METADATA
qcsapphire-1.0.1.dist-info/WHEEL
qcsapphire-1.0.1.dist-info/top_level.txt
qcsapphire-1.0.1.dist-info/RECORD
